clean_ipynb/__init__.py
clean_ipynb/clean_ipynb.py
cleanipynb-0.4.2.dist-info/DESCRIPTION.rst
cleanipynb-0.4.2.dist-info/METADATA
cleanipynb-0.4.2.dist-info/RECORD
cleanipynb-0.4.2.dist-info/WHEEL
cleanipynb-0.4.2.dist-info/entry_points.txt
cleanipynb-0.4.2.dist-info/metadata.json
cleanipynb-0.4.2.dist-info/top_level.txt
