Metadata-Version: 2.0
Name: cleanipynb
Version: 0.4.2
Summary: Cleanup imports in jupyter notebooks
Home-page: https://github.com/i008/clean_ipynb
Author: Jakub Cieslik
Author-email: kubacieslik@gmail.com
License: MIT license
Keywords: cleanipynb
Platform: UNKNOWN
Classifier: Development Status :: 2 - Pre-Alpha
Classifier: Intended Audience :: Developers
Classifier: License :: OSI Approved :: MIT License
Classifier: Natural Language :: English
Classifier: Programming Language :: Python :: 3.6
Classifier: Programming Language :: Python :: 3.7
Requires-Dist: jupytext
Requires-Dist: importanize
Requires-Dist: autoflake
